snowglobe/telemetry/openinference/__init__.py
snowglobe/telemetry/openinference/openinference_instrumentor.py
snowglobe/telemetry/openinference/openinference_utils.py
snowglobe_telemetry_openinference-0.0.1.dist-info/licenses/LICENSE
snowglobe_telemetry_openinference-0.0.1.dist-info/METADATA
snowglobe_telemetry_openinference-0.0.1.dist-info/WHEEL
snowglobe_telemetry_openinference-0.0.1.dist-info/top_level.txt
snowglobe_telemetry_openinference-0.0.1.dist-info/RECORD
