Metadata-Version: 2.4
Name: snowglobe-telemetry-openinference
Version: 0.0.1
Summary: OpenInference instrumentation for the snowglobe client
Author-email: Guardrails AI <contact@guardrailsai.com>
License: MIT License
Requires-Python: >=3.9
License-File: LICENSE
Requires-Dist: opentelemetry-api
Requires-Dist: opentelemetry-sdk
Requires-Dist: opentelemetry-exporter-otlp
Requires-Dist: opentelemetry-instrumentation
Requires-Dist: opentelemetry-semantic-conventions
Requires-Dist: openinference-instrumentation>=0.1.27
Requires-Dist: openinference-semantic-conventions>=0.1.17
Requires-Dist: packaging
Provides-Extra: dev
Requires-Dist: snowglobe>=0.4.16; extra == "dev"
Requires-Dist: ruff<0.2.0,>=0.1.0; extra == "dev"
Requires-Dist: mypy<2.0.0,>=1.5.0; extra == "dev"
Requires-Dist: pre-commit>=4.1.0; extra == "dev"
Requires-Dist: coverage>=7.6.12; extra == "dev"
Requires-Dist: pyright[nodejs]>=1.1.396; extra == "dev"
Dynamic: license-file
